lavagame/__init__.py
lavagame/example.py
lavagame-1.0.1.dist-info/LICENSE
lavagame-1.0.1.dist-info/METADATA
lavagame-1.0.1.dist-info/WHEEL
lavagame-1.0.1.dist-info/top_level.txt
lavagame-1.0.1.dist-info/RECORD
