Metadata-Version: 2.1
Name: lavagame
Version: 1.0.1
Summary: Lavagame เข้าสู่ระบบ สมัคร เครดิตฟรี ชวนเพื่อน โปร 100
Author-email: lavagame <lavagame@example.com>
Project-URL: Homepage, https://github.com/
Classifier: Programming Language :: Python :: 3
Classifier: License :: OSI Approved :: MIT License
Classifier: Operating System :: OS Independent
Requires-Python: >=3.7
License-File: LICENSE
